setup.py
test/test_cn_squant2_run.py
test/test_cn_squant2_run_text.py
zipline_cn_databundle/__init__.py
zipline_cn_databundle/all_stocks.py
zipline_cn_databundle/loader.py
zipline_cn_databundle/squant_source.py
zipline_cn_databundle/tushare_source.py
zipline_cn_databundle/yahoo.py
zipline_cn_databundle.egg-info/PKG-INFO
zipline_cn_databundle.egg-info/SOURCES.txt
zipline_cn_databundle.egg-info/dependency_links.txt
zipline_cn_databundle.egg-info/entry_points.txt
zipline_cn_databundle.egg-info/requires.txt
zipline_cn_databundle.egg-info/top_level.txt
zipline_cn_databundle/index_list/__init__.py
zipline_cn_databundle/tdx/__init__.py
zipline_cn_databundle/tdx/reader.py