Metadata-Version: 1.0
Name: zipline-cn-databundle
Version: 0.5
Summary: ingest zipline databundle source for chinese market
Home-page: UNKNOWN
Author: RainX
Author-email: UNKNOWN
License: UNKNOWN
Platform: UNKNOWN
